connect_4/__init__.py
connect_4/board.py
connect_4/clear_screen.py
connect_4/connect_four_interface.py
connect_4/game_engine.py
connect_4/interface.py
connect_4/player.py
connect_4/random_bot.py
connect_4-0.1.0b3.dist-info/LICENSE
connect_4-0.1.0b3.dist-info/METADATA
connect_4-0.1.0b3.dist-info/WHEEL
connect_4-0.1.0b3.dist-info/entry_points.txt
connect_4-0.1.0b3.dist-info/top_level.txt
connect_4-0.1.0b3.dist-info/RECORD
