Metadata-Version: 2.1
Name: connect-4
Version: 0.1.0b3
Summary: A connect 4 CLI game
Home-page: https://gitlab.com/ritwikgopi/connect-4
Author: Ritwik G
Author-email: i@ritwikg.com
License: UNKNOWN
Platform: UNKNOWN
Classifier: Programming Language :: Python :: 3
Classifier: License :: OSI Approved :: MIT License
Classifier: Operating System :: OS Independent
Requires-Python: >=3.6
